src/stash-empornium/emp_stash_fill.py
stash_empornium-0.dist-info/METADATA
stash_empornium-0.dist-info/WHEEL
stash_empornium-0.dist-info/licenses/LICENSE
stash_empornium-0.dist-info/RECORD
