Metadata-Version: 2.1
Name: stash-empornium
Version: 0
Summary: Backend server for EMP Stash upload helper userscript
Project-URL: Homepage, https://github.com/bdbenim/stash-empornium
Project-URL: Issue Tracker, https://github.com/bdbenim/stash-empornium/issues
Project-URL: Repository, https://github.com/bdbenim/stash-empornium.git
Author: bdbenim
License-File: LICENSE
Classifier: Development Status :: 3 - Alpha
Classifier: License :: OSI Approved :: The Unlicense (Unlicense)
Classifier: Operating System :: OS Independent
Classifier: Programming Language :: Python :: 3
Classifier: Topic :: Communications :: File Sharing
Requires-Python: >=3.10
Provides-Extra: production
Requires-Dist: waitress; extra == 'production'
